{
  "success": true,
  "message": "Image details",
  "data": {
    "imageid": "024BZD94",
    "image_file": "024BZD94.jpg",
    "mime": "image/jpeg",
    "width": "1552",
    "height": "1080",
    "details": {
      "title": {
        "filter": "commercial",
        "filter_name": "Title",
        "values": [
          {
            "display_value": "Be Kids",
            "search_value": "56465"
          }
        ]
      },
      "full_title": "Otrivin - Airbubble - “Be Kids”",
      "media_type": {
        "filter": "media_type",
        "filter_name": "Media Type",
        "values": [
          {
            "display_value": "commercial",
            "search_value": "commercial"
          }
        ]
      },
      "year": {
        "filter": "year",
        "filter_name": "Release Year",
        "values": [
          {
            "display_value": "2021",
            "search_value": "2021"
          }
        ]
      },
      "shade": {
        "filter": "shade",
        "filter_name": "Shade",
        "values": [
          {
            "display_value": "141414",
            "search_value": "141414~25~1"
          },
          {
            "display_value": "5d5d5d",
            "search_value": "5d5d5d~25~1"
          },
          {
            "display_value": "9c9c9c",
            "search_value": "9c9c9c~25~1"
          },
          {
            "display_value": "cacaca",
            "search_value": "cacaca~25~1"
          }
        ]
      },
      "shot_info": {
        "description": "Shot info",
        "tags": {
          "filter": "search",
          "filter_name": "Tags",
          "values": [
            {
              "display_value": "black and white",
              "search_value": "\"black+and+white\""
            },
            {
              "display_value": "side profile",
              "search_value": "\"side+profile\""
            },
            {
              "display_value": "smiling",
              "search_value": "smiling"
            },
            {
              "display_value": "long hair",
              "search_value": "\"long+hair\""
            },
            {
              "display_value": "white letters",
              "search_value": "\"white+letters\""
            },
            {
              "display_value": "looking up",
              "search_value": "\"looking+up\""
            },
            {
              "display_value": "look of wonder",
              "search_value": "\"look+of+wonder\""
            },
            {
              "display_value": "body of water",
              "search_value": "\"body+of+water\""
            }
          ]
        },
        "time_of_day": {
          "filter": "time_of_day",
          "filter_name": "Time of Day",
          "values": [
            {
              "display_value": "Day",
              "search_value": "Day"
            }
          ]
        },
        "int_ext": {
          "filter": "int_ext",
          "filter_name": "Interior/Exterior",
          "values": [
            {
              "display_value": "Exterior",
              "search_value": "Exterior"
            }
          ]
        },
        "color": {
          "filter": "color",
          "filter_name": "Color",
          "values": [
            {
              "display_value": "Desaturated",
              "search_value": "Desaturated"
            },
            {
              "display_value": "Black and White",
              "search_value": "Black+and+White"
            }
          ]
        },
        "frame_size": {
          "filter": "frame_size",
          "filter_name": "Frame Size",
          "values": [
            {
              "display_value": "Close Up",
              "search_value": "Close+Up"
            },
            {
              "display_value": "Extreme Close Up",
              "search_value": "Extreme+Close+Up"
            }
          ]
        },
        "lens_type": {
          "filter": "lens_type",
          "filter_name": "Lens Size",
          "values": [
            {
              "display_value": "Medium",
              "search_value": "Medium"
            },
            {
              "display_value": "Long Lens",
              "search_value": "Long+Lens"
            }
          ]
        },
        "composition": {
          "filter": "composition",
          "filter_name": "Composition",
          "values": [
            {
              "display_value": "Center",
              "search_value": "Center"
            }
          ]
        },
        "shot_type": {
          "filter": "shot_type",
          "filter_name": "Shot Type",
          "values": [
            {
              "display_value": "Clean single",
              "search_value": "Clean+single"
            }
          ]
        },
        "lighting": {
          "filter": "lighting",
          "filter_name": "Lighting",
          "values": [
            {
              "display_value": "Soft light",
              "search_value": "Soft+light"
            },
            {
              "display_value": "Side light",
              "search_value": "Side+light"
            }
          ]
        },
        "lighting_type": {
          "filter": "lighting_type",
          "filter_name": "Lighting Type",
          "values": [
            {
              "display_value": "Daylight",
              "search_value": "Daylight"
            },
            {
              "display_value": "Overcast",
              "search_value": "Overcast"
            }
          ]
        },
        "aspect_ratio": {
          "filter": "aspect_ratio",
          "filter_name": "Aspect Ratio",
          "values": [
            {
              "display_value": "1.43",
              "search_value": "1.43"
            }
          ]
        },
        "setting": {
          "filter": "setting",
          "filter_name": "Set",
          "values": [
            {
              "display_value": "Lakeside",
              "search_value": "Lakeside"
            }
          ]
        },
        "location_type": {
          "filter": "location_type",
          "filter_name": "Location Type",
          "values": [
            {
              "display_value": "Location",
              "search_value": "Location"
            }
          ]
        },
        "shot_time": {
          "filter": "n/a",
          "filter_name": "Shot Time",
          "values": [
            {
              "display_value": "00:00:57",
              "search_value": "n/a"
            }
          ]
        }
      },
      "title_info": {
        "description": "Commercial info",
        "genre": {
          "filter": "genre",
          "filter_name": "Genre",
          "values": [
            {
              "display_value": "Health / Beauty",
              "search_value": "Commercial+-+Health+%2F+Beauty"
            },
            {
              "display_value": "Pharmaceutical",
              "search_value": "Commercial+-+Pharmaceutical"
            }
          ]
        },
        "director": {
          "filter": "director",
          "filter_name": "Director",
          "values": [
            {
              "display_value": "Tino",
              "search_value": "Tino"
            },
            {
              "display_value": "Airton Carmignani",
              "search_value": "Airton+Carmignani"
            }
          ]
        },
        "cinematographer": {
          "filter": "cinematographer",
          "filter_name": "Cinematographer",
          "values": [
            {
              "display_value": "Sveta Aparina",
              "search_value": "Sveta+Aparina"
            }
          ]
        },
        "production_designer": {
          "filter": "production_designer",
          "filter_name": "Production Designer",
          "values": [
            {
              "display_value": "Natasha Makhovska",
              "search_value": "Natasha+Makhovska"
            }
          ]
        },
        "costume_designer": {
          "filter": "costume_designer",
          "filter_name": "Costume Designer",
          "values": [
            {
              "display_value": "Dasha Filshina",
              "search_value": "Dasha+Filshina"
            }
          ]
        },
        "editor": {
          "filter": "editor",
          "filter_name": "Editor",
          "values": [
            {
              "display_value": "Dan Abraham",
              "search_value": "Dan+Abraham"
            }
          ]
        },
        "brand": {
          "filter": "brand",
          "filter_name": "Brand",
          "values": [
            {
              "display_value": "Otrivin",
              "search_value": "Otrivin"
            }
          ]
        },
        "product": {
          "filter": "product",
          "filter_name": "Product",
          "values": [
            {
              "display_value": "Airbubble",
              "search_value": "Airbubble"
            }
          ]
        }
      }
    }
  }
}