{
  "success": true,
  "message": "Image details",
  "data": {
    "imageid": "04A760MB",
    "image_file": "04A760MB.jpg",
    "mime": "image/jpeg",
    "width": "1920",
    "height": "1080",
    "details": {
      "title": {
        "filter": "music video",
        "filter_name": "Title",
        "values": [
          {
            "display_value": "Sundress",
            "search_value": "49760"
          }
        ]
      },
      "full_title": "A$AP Rocky - “Sundress”",
      "media_type": {
        "filter": "media_type",
        "filter_name": "Media Type",
        "values": [
          {
            "display_value": "music video",
            "search_value": "music+video"
          }
        ]
      },
      "year": {
        "filter": "year",
        "filter_name": "Release Year",
        "values": [
          {
            "display_value": "2018",
            "search_value": "2018"
          }
        ]
      },
      "shade": {
        "filter": "shade",
        "filter_name": "Shade",
        "values": [
          {
            "display_value": "050a09",
            "search_value": "050a09~25~1"
          },
          {
            "display_value": "040a0d",
            "search_value": "040a0d~25~1"
          },
          {
            "display_value": "2d070a",
            "search_value": "2d070a~25~1"
          },
          {
            "display_value": "25130b",
            "search_value": "25130b~25~1"
          },
          {
            "display_value": "504328",
            "search_value": "504328~25~1"
          },
          {
            "display_value": "871c16",
            "search_value": "871c16~25~1"
          },
          {
            "display_value": "435377",
            "search_value": "435377~25~1"
          },
          {
            "display_value": "a10007",
            "search_value": "a10007~25~1"
          },
          {
            "display_value": "6c4d39",
            "search_value": "6c4d39~25~1"
          },
          {
            "display_value": "aa3245",
            "search_value": "aa3245~25~1"
          },
          {
            "display_value": "c95b4d",
            "search_value": "c95b4d~25~1"
          },
          {
            "display_value": "d54c5e",
            "search_value": "d54c5e~25~1"
          },
          {
            "display_value": "dc8273",
            "search_value": "dc8273~25~1"
          },
          {
            "display_value": "ea7883",
            "search_value": "ea7883~25~1"
          },
          {
            "display_value": "f5929a",
            "search_value": "f5929a~25~1"
          }
        ]
      },
      "shot_info": {
        "description": "Shot info",
        "tags": {
          "filter": "search",
          "filter_name": "Tags",
          "values": [
            {
              "display_value": "hair tied back",
              "search_value": "\"hair+tied+back\""
            },
            {
              "display_value": "hoop earrings",
              "search_value": "\"hoop+earrings\""
            },
            {
              "display_value": "shape",
              "search_value": "shape"
            },
            {
              "display_value": "distortion",
              "search_value": "distortion"
            },
            {
              "display_value": "warped image",
              "search_value": "\"warped+image\""
            },
            {
              "display_value": "circle",
              "search_value": "circle"
            },
            {
              "display_value": "cigarette burn",
              "search_value": "\"cigarette+burn\""
            }
          ]
        },
        "actors": {
          "filter": "actors",
          "filter_name": "Actors",
          "values": [
            {
              "display_value": "Kesewa Aboah",
              "search_value": "Kesewa+Aboah"
            }
          ]
        },
        "time_period": {
          "filter": "time_period",
          "filter_name": "Time Period",
          "values": [
            {
              "display_value": "2010s",
              "search_value": "2010s"
            }
          ]
        },
        "time_of_day": {
          "filter": "time_of_day",
          "filter_name": "Time of Day",
          "values": [
            {
              "display_value": "Night",
              "search_value": "Night"
            }
          ]
        },
        "int_ext": {
          "filter": "int_ext",
          "filter_name": "Interior/Exterior",
          "values": [
            {
              "display_value": "Exterior",
              "search_value": "Exterior"
            }
          ]
        },
        "color": {
          "filter": "color",
          "filter_name": "Color",
          "values": [
            {
              "display_value": "Warm",
              "search_value": "Warm"
            },
            {
              "display_value": "Saturated",
              "search_value": "Saturated"
            },
            {
              "display_value": "Red",
              "search_value": "Red"
            },
            {
              "display_value": "Blue",
              "search_value": "Blue"
            },
            {
              "display_value": "Pink",
              "search_value": "Pink"
            }
          ]
        },
        "frame_size": {
          "filter": "frame_size",
          "filter_name": "Frame Size",
          "values": [
            {
              "display_value": "Close Up",
              "search_value": "Close+Up"
            }
          ]
        },
        "lens_type": {
          "filter": "lens_type",
          "filter_name": "Lens Size",
          "values": [
            {
              "display_value": "Long Lens",
              "search_value": "Long+Lens"
            }
          ]
        },
        "composition": {
          "filter": "composition",
          "filter_name": "Composition",
          "values": [
            {
              "display_value": "Center",
              "search_value": "Center"
            }
          ]
        },
        "shot_type": {
          "filter": "shot_type",
          "filter_name": "Shot Type",
          "values": [
            {
              "display_value": "Clean single",
              "search_value": "Clean+single"
            },
            {
              "display_value": "Low angle",
              "search_value": "Low+angle"
            }
          ]
        },
        "lighting": {
          "filter": "lighting",
          "filter_name": "Lighting",
          "values": [
            {
              "display_value": "High contrast",
              "search_value": "High+contrast"
            },
            {
              "display_value": "Side light",
              "search_value": "Side+light"
            },
            {
              "display_value": "Edge light",
              "search_value": "Edge+light"
            }
          ]
        },
        "lighting_type": {
          "filter": "lighting_type",
          "filter_name": "Lighting Type",
          "values": [
            {
              "display_value": "Artificial light",
              "search_value": "Artificial+light"
            }
          ]
        },
        "aspect_ratio": {
          "filter": "aspect_ratio",
          "filter_name": "Aspect Ratio",
          "values": [
            {
              "display_value": "1.78",
              "search_value": "1.78"
            }
          ]
        },
        "setting": {
          "filter": "setting",
          "filter_name": "Set",
          "values": [
            {
              "display_value": "City Street",
              "search_value": "City+Street"
            }
          ]
        },
        "location_type": {
          "filter": "location_type",
          "filter_name": "Location Type",
          "values": [
            {
              "display_value": "Location",
              "search_value": "Location"
            }
          ]
        },
        "shot_time": {
          "filter": "n/a",
          "filter_name": "Shot Time",
          "values": [
            {
              "display_value": "00:02:48",
              "search_value": "n/a"
            }
          ]
        }
      },
      "title_info": {
        "description": "Music Video info",
        "genre": {
          "filter": "genre",
          "filter_name": "Genre",
          "values": [
            {
              "display_value": "Concept",
              "search_value": "Music+Video+-+Concept"
            }
          ]
        },
        "director": {
          "filter": "director",
          "filter_name": "Director",
          "values": [
            {
              "display_value": "Frank Lebon",
              "search_value": "Frank+Lebon"
            }
          ]
        },
        "cinematographer": {
          "filter": "cinematographer",
          "filter_name": "Cinematographer",
          "values": [
            {
              "display_value": "Molly Manning Walker",
              "search_value": "Molly+Manning+Walker"
            }
          ]
        },
        "editor": {
          "filter": "editor",
          "filter_name": "Editor",
          "values": [
            {
              "display_value": "Frank Lebon",
              "search_value": "Frank+Lebon"
            }
          ]
        },
        "artist": {
          "filter": "artist",
          "filter_name": "Artist",
          "values": [
            {
              "display_value": "A$AP Rocky",
              "search_value": "A%24AP+Rocky"
            }
          ]
        }
      }
    }
  }
}